catdog/version.py
catdog-1.0.4.dist-info/METADATA
catdog-1.0.4.dist-info/WHEEL
catdog-1.0.4.dist-info/top_level.txt
catdog-1.0.4.dist-info/RECORD
