Metadata-Version: 2.2
Name: catdog
Version: 1.0.4
Summary: A simple library for cat and dog image classification
Home-page: https://github.com/BogdanSuchko/catdog
Author: Julfy
Author-email: bahdan.suchko@yandex.by
Classifier: Programming Language :: Python :: 3
Classifier: License :: OSI Approved :: MIT License
Classifier: Operating System :: OS Independent
Requires-Dist: torch
Requires-Dist: torchvision
Requires-Dist: Pillow
Dynamic: author
Dynamic: author-email
Dynamic: classifier
Dynamic: description
Dynamic: description-content-type
Dynamic: home-page
Dynamic: requires-dist
Dynamic: summary
